Metadata-Version: 2.1
Name: colorsmaster
Version: 1.9
Summary: by Oxygen1337
Author-email: <Oxygen1337@gmail.com>
License: Eclipse Public License 2.0
Keywords: cli,fade,colors,terminal,tui
